argentcontentbaba/__init__.py
argentcontentbaba/main.py
argentcontentbaba-0.1.0.dist-info/METADATA
argentcontentbaba-0.1.0.dist-info/WHEEL
argentcontentbaba-0.1.0.dist-info/RECORD
